st_dropfill_textarea/__init__.py
st_dropfill_textarea/frontend/dist/index.html
st_dropfill_textarea/frontend/dist/css/app.d9946277.css
st_dropfill_textarea/frontend/dist/js/app.7130c015.js
st_dropfill_textarea/frontend/dist/js/app.7130c015.js.map
st_dropfill_textarea/frontend/dist/js/chunk-vendors.e7772cca.js
st_dropfill_textarea/frontend/dist/js/chunk-vendors.e7772cca.js.map
streamlit_component_dropfilltextarea-0.3.0.dist-info/LICENSE
streamlit_component_dropfilltextarea-0.3.0.dist-info/METADATA
streamlit_component_dropfilltextarea-0.3.0.dist-info/WHEEL
streamlit_component_dropfilltextarea-0.3.0.dist-info/top_level.txt
streamlit_component_dropfilltextarea-0.3.0.dist-info/RECORD
