Metadata-Version: 2.1
Name: streamlit-component-dropfilltextarea
Version: 0.3.0
Summary: Streamlit's DropFillTextarea lets users drag and drop files onto a text area, filling in text quickly. It populates text areas with pre-existing files, reducing manual input, while offering layout customization. Ideal for simplifying workflows for both developers and users.
Author: Jiayi Chen
Author-email: chenjiayi_344@hotmail.com
Requires-Python: >=3.7
License-File: LICENSE
Requires-Dist: streamlit (>=1.2)
Requires-Dist: jinja2
